magic_ocr/__init__.py
magic_ocr/base.py
magic_ocr/config.py
magic_ocr/prompts.py
magic_ocr/utils.py
magic_ocr/mcp/__init__.py
magic_ocr/mcp/server.py
magic_ocr/mcp/tools.py
magic_ocr/providers/__init__.py
magic_ocr/providers/gcp.py
magic_ocr/providers/gemini.py
magic_ocr/providers/openai.py
magic_ocr-0.1.1.dist-info/licenses/LICENSE
magic_ocr-0.1.1.dist-info/METADATA
magic_ocr-0.1.1.dist-info/WHEEL
magic_ocr-0.1.1.dist-info/entry_points.txt
magic_ocr-0.1.1.dist-info/top_level.txt
magic_ocr-0.1.1.dist-info/RECORD
