Metadata-Version: 2.4
Name: magic-ocr
Version: 0.1.1
Summary: Multi-provider OCR library with MCP server support
Author-email: Frank Qing <qyhfrank@gmail.com>
License: MIT
Keywords: ocr,mcp,gemini,openai,vision
Classifier: Development Status :: 3 - Alpha
Classifier: Intended Audience :: Developers
Classifier: License :: OSI Approved :: MIT License
Classifier: Programming Language :: Python :: 3
Classifier: Programming Language :: Python :: 3.8
Classifier: Programming Language :: Python :: 3.9
Classifier: Programming Language :: Python :: 3.10
Classifier: Programming Language :: Python :: 3.11
Classifier: Programming Language :: Python :: 3.12
Requires-Python: >=3.8
License-File: LICENSE
Requires-Dist: openai>=1.0.0
Requires-Dist: httpx>=0.28.0
Requires-Dist: fastmcp>=0.2.0
Requires-Dist: Pillow>=10.0.0
Requires-Dist: python-dotenv>=1.0.0
Requires-Dist: google-genai>=1.0.0
Requires-Dist: google-cloud-vision>=3.0.0
Provides-Extra: dev
Requires-Dist: pytest>=7.0.0; extra == "dev"
Requires-Dist: pytest-asyncio>=0.21.0; extra == "dev"
Dynamic: license-file
